exsited/__init__.py
exsited/common/__init__.py
exsited/common/ab_exception.py
exsited/common/sdk_conf.py
exsited/common/sdk_console.py
exsited/common/sdk_const.py
exsited/common/sdk_util.py
exsited/exsited/__init__.py
exsited/exsited/exsited_sdk.py
exsited/exsited/account/__init__.py
exsited/exsited/account/account.py
exsited/exsited/account/account_api_url.py
exsited/exsited/account/dto/__init__.py
exsited/exsited/account/dto/account_dto.py
exsited/exsited/account/dto/account_nested_dto.py
exsited/exsited/auth/__init__.py
exsited/exsited/auth/auth_api_url.py
exsited/exsited/auth/dto/__init__.py
exsited/exsited/auth/dto/token_dto.py
exsited/exsited/common/__init__.py
exsited/exsited/common/common_api_url.py
exsited/exsited/common/common_enum.py
exsited/exsited/common/dto/__init__.py
exsited/exsited/common/dto/common_dto.py
exsited/exsited/credit_note/__init__.py
exsited/exsited/credit_note/credit_note.py
exsited/exsited/credit_note/credit_note_api_url.py
exsited/exsited/credit_note/dto/__init__.py
exsited/exsited/credit_note/dto/credit_note_dto.py
exsited/exsited/custom_attributes/__init__.py
exsited/exsited/custom_attributes/custom_attributes.py
exsited/exsited/custom_attributes/custom_attributes_api_url.py
exsited/exsited/custom_attributes/dto/__init__.py
exsited/exsited/custom_attributes/dto/custom_attributes_dto.py
exsited/exsited/custom_component/__init__.py
exsited/exsited/custom_component/custom_component.py
exsited/exsited/custom_component/custom_component_api_url.py
exsited/exsited/custom_component/dto/__init__.py
exsited/exsited/custom_component/dto/custom_component_dto.py
exsited/exsited/custom_objects/__init__.py
exsited/exsited/custom_objects/custom_objects.py
exsited/exsited/custom_objects/custom_objects_api_url.py
exsited/exsited/custom_objects/dto/__init__.py
exsited/exsited/custom_objects/dto/custom_objects_dto.py
exsited/exsited/custom_objects_in_account/__init__.py
exsited/exsited/custom_objects_in_account/dto/__init__.py
exsited-1.0.33.dist-info/licenses/LICENSE
exsited-1.0.33.dist-info/METADATA
exsited-1.0.33.dist-info/WHEEL
exsited-1.0.33.dist-info/top_level.txt
exsited-1.0.33.dist-info/RECORD
