Metadata-Version: 2.4
Name: exsited
Version: 1.0.33
Summary: Exsited SDK
Home-page: https://github.com/exsited/exsited-python
Author: Ashiq Rahman
Author-email: ashiq@webalive.com.au
Project-URL: Documentation, https://developer.exsited.com/exsited-sdk-introduction
Platform: any
Classifier: Programming Language :: Python :: 3
Classifier: License :: OSI Approved :: MIT License
Classifier: Operating System :: OS Independent
License-File: LICENSE
Requires-Dist: requests
Requires-Dist: setuptools
Requires-Dist: peewee
Requires-Dist: mysql-connector-python
Requires-Dist: portalocker
Dynamic: author
Dynamic: author-email
Dynamic: classifier
Dynamic: description
Dynamic: description-content-type
Dynamic: home-page
Dynamic: license-file
Dynamic: platform
Dynamic: project-url
Dynamic: requires-dist
Dynamic: summary
